{"cameraMode":{"drawMode":0,"name":"Shaded","section":"Shading Mode"},"sceneLighting":true,"audioPlay":false,"sceneViewState":{"m_AlwaysRefresh":false,"showFog":false,"showSkybox":false,"showFlares":false,"showImageEffects":false,"showParticleSystems":false,"showVisualEffectGraphs":true,"m_FxEnabled":true},"in2DMode":false,"pivot":{"x":12.399999618530274,"y":0.47999998927116396,"z":-6.239999771118164},"rotation":{"x":-0.5004385113716126,"y":0.08337266743183136,"z":-0.04849046468734741,"w":-0.8603906631469727},"size":1.004066824913025,"orthographic":false}